{
    "Jeta": "zeTa",
    "arjo": "arrzo",
    "aro": "arO",
    "bandor": "ba^dor",
    "bari": "baRi",
    "benche": "be^ce",
    "besi": "beSi",
    "bhara": "bhaRa",
    "bhuri": "bhu^Ri",
    "birendro": "bIrendro",
    "bnara": "ba^Ra",
    "boidyobati": "bOIdyobaTi",
    "boidyopara": "bOIdyopaRa",
    "bollo": "bololO",
    "bolo": "bOlO",
    "boro": "boRo",
    "boudi": "bOUdi",
    "boudir": "bOUdir",
    "byabsa": "bZbsa",
    "byabsay": "bZbsay",
    "chan": "can",
    "chand": "ca^d",
    "chanda": "ca^da",
    "char": "chaR",
    "chara": "chaRa",
    "chhan": "chan",
    "chinta": "cinta",
    "chitgrosto": "chiTgrosto",
    "chitpur": "cit``pur",
    "chod": "cOd",
    "chole": "cole",
    "chondonnogor": "condon`nogor",
    "choto": "chOTo",
    "choturthi": "coturrthI",
    "chuchura": "cu^cuRa",
    "chuti": "chuTi",
    "dainhat": "da^inhaT",
    "dankuni": "Dan`kuni",
    "dansi": "Da^sI",
    "dant": "da^t",
    "dekhabo": "dekhabO",
    "dhokano": "DhokanO",
    "digha": "dIgha",
    "dokshinbari": "doKSHiN`baRi",
    "dokshineswar": "doKSHiNeSWr",
    "doshomi": "doshomI",
    "duto": "duTO",
    "ekhono": "ekhonO",
    "ekso": "ekSO",
    "ekta": "ek`Ta",
    "gache": "geche",
    "gari": "gaRi",
    "ghanti": "gha^Ti",
    "gnuro": "gu^RO",
    "gora": "gORa",
    "gulo": "gulO",
    "gun": "guN",
    "gur": "guR",
    "holo": "holO",
    "hoyto": "hoytO",
    "ja": "za",
    "jabar": "zabar",
    "jabi": "zabi",
    "jabo": "zabo",
    "jader": "zader",
    "jah": "ja",
    "jamon": "zemon",
    "jaowa": "zaoya",
    "jaowar": "zaoyar",
    "japani": "japanI",
    "jati": "jati",
    "jatiyo": "jatIyo",
    "jawa": "zaoya",
    "jay": "zay",
    "jeno": "zeno",
    "jete": "zete",
    "jog": "zOg",
    "jomraja": "zom`raja",
    "jonne": "jonZe",
    "jotota": "zotoTa",
    "jouno": "zOUno",
    "judhistir": "zudhiSHThir",
    "kI": "kI",
    "kalo": "kalO",
    "kamarkundu": "kamarkuNDu",
    "kancha": "ka^ca",
    "kate": "kaTe",
    "khanri": "kha^Ri",
    "knuri": "ku^Ri",
    "koi": "kOI",
    "kono": "kOnO",
    "koshto": "koSHTo",
    "kosto": "koSHTo",
    "koti": "kOTi",
    "kshetre": "KSHetre",
    "kshomota": "KSHomota",
    "loke": "lOke",
    "mankundu": "man`kuNDu",
    "mash": "mas",
    "masher": "maser",
    "memari": "memarI",
    "misti": "miSHTi",
    "moida": "moyda",
    "morcha": "mOrrca",
    "mrito": "mrrito",
    "mukharji": "mukharrjI",
    "nari": "narI",
    "nich": "nic",
    "niche": "nIce",
    "nichu": "nicu",
    "nobomi": "nobomI",
    "norbore": "noRboRe",
    "oder": "Oder",
    "om": "O^",
    "onader": "O^nader",
    "onar": "O^nar",
    "ora": "Ora",
    "osonko": "oSonko",
    "ostomi": "oSHTomI",
    "ota": "OTa",
    "paltano": "palTanO",
    "panch": "pa^c",
    "pandua": "paNDuya",
    "panjabi": "panjabI",
    "para": "paRa",
    "paro": "parO",
    "pathiye": "paThiye",
    "pirtola": "pIrrtola",
    "posha": "pOSha",
    "pounchabo": "pOU^chabO",
    "pounche": "pOU^che",
    "pouncheche": "pOU^cheche",
    "pounchecho": "pOU^chechO",
    "pounchobe": "pOU^chObe",
    "prithibi": "prrithibI",
    "pujo": "pujO",
    "punohmulyaon": "puno:mUlyayon",
    "purbe": "pUrrbe",
    "purbo": "pUrrbo",
    "purono": "purOnO",
    "santragachi": "sa^t`ragachi",
    "sari": "shaRi",
    "seoraphuli": "SeoRaphuli",
    "sesh": "sheSh",
    "shari": "shaRi",
    "shilpi": "shilpI",
    "shishyo": "shiShZo",
    "shnar": "Sha^R",
    "shrishti": "shrriSHTi",
    "singho": "sing`ho",
    "sobder": "shobder",
    "sojja": "shozZa",
    "songho": "song`gho",
    "soptomi": "soptomI",
    "soshibabu": "SoshIbabu",
    "sosthi": "ShoSHThI",
    "subornomrigi": "suborrNomrrigI",
    "suchi": "sUci",
    "sudhu": "Sudhu",
    "suni": "Suni",
    "sunnyo": "Sunyo",
    "suru": "shuru",
    "taka": "Taka",
    "tarokeswor": "tarokeSWor",
    "tay": "Tay",
    "thik": "Thik",
    "tomar": "tOmar",
    "totto": "tottwo"
}
